fabric_slack_tools/__init__.py
fabric_slack_tools-0.2.2.dist-info/LICENSE
fabric_slack_tools-0.2.2.dist-info/METADATA
fabric_slack_tools-0.2.2.dist-info/WHEEL
fabric_slack_tools-0.2.2.dist-info/top_level.txt
fabric_slack_tools-0.2.2.dist-info/RECORD
