Metadata-Version: 2.1
Name: fabric-slack-tools
Version: 0.2.2
Summary: Fabric integration with Slack
Home-page: http://github.com/erans/fabric-slack-tools
Author: Eran Sandler
Author-email: eran@sandler.co.il
License: UNKNOWN
Platform: UNKNOWN
Classifier: Development Status :: 5 - Production/Stable
Classifier: Environment :: Console
Classifier: Intended Audience :: Developers
Classifier: Intended Audience :: System Administrators
Classifier: Operating System :: OS Independent
Classifier: Programming Language :: Python :: 2.7
Classifier: Topic :: System :: Clustering
Classifier: Topic :: System :: Systems Administration
Classifier: Topic :: Utilities
Provides-Extra: test
Requires-Dist: nose ; extra == 'test'
Requires-Dist: coverage ; extra == 'test'
Requires-Dist: mock ; extra == 'test'
